simple_sftp/__init__.py
simple_sftp/__main__.py
simple_sftp/client.py
simple_sftp-0.1.3.dist-info/METADATA
simple_sftp-0.1.3.dist-info/WHEEL
simple_sftp-0.1.3.dist-info/entry_points.txt
simple_sftp-0.1.3.dist-info/top_level.txt
simple_sftp-0.1.3.dist-info/RECORD
