Metadata-Version: 2.4
Name: simple-sftp
Version: 0.1.3
Summary: Simple way to handle sftp with python
Author: Wellbia.com Co.,Ltd.
Author-email: opensource@wellbia.com
Classifier: License :: OSI Approved :: MIT License
Classifier: Programming Language :: Python :: 3.6
Classifier: Programming Language :: Python :: 3.7
Classifier: Programming Language :: Python :: 3.8
Classifier: Programming Language :: Python :: 3.9
Requires-Dist: paramiko
Dynamic: author
Dynamic: author-email
Dynamic: classifier
Dynamic: description
Dynamic: description-content-type
Dynamic: requires-dist
Dynamic: summary
